i3hub.py
i3hub-3.1.1.data/data/share/i3hub/extensions/hub_status.py
i3hub-3.1.1.data/data/share/i3hub/extensions/keyboard_layout_switcher.py
i3hub-3.1.1.data/data/share/i3hub/extensions/nop_binding.py
i3hub-3.1.1.data/data/share/i3hub/extensions/split_alternator.py
i3hub-3.1.1.data/data/share/i3hub/extensions/status_wrapper.py
i3hub-3.1.1.data/data/share/i3hub/extensions/workspace_master.py
i3hub-3.1.1.dist-info/DESCRIPTION.rst
i3hub-3.1.1.dist-info/METADATA
i3hub-3.1.1.dist-info/RECORD
i3hub-3.1.1.dist-info/WHEEL
i3hub-3.1.1.dist-info/entry_points.txt
i3hub-3.1.1.dist-info/metadata.json
i3hub-3.1.1.dist-info/top_level.txt
